LICENSE
README.md
setup.py
jxWebUI/__init__.py
jxWebUI.egg-info/PKG-INFO
jxWebUI.egg-info/SOURCES.txt
jxWebUI.egg-info/dependency_links.txt
jxWebUI.egg-info/requires.txt
jxWebUI.egg-info/top_level.txt
jxWebUI/docs/jxORM使用说明/整体说明.1.md
jxWebUI/docs/jxORM使用说明/查询数据.3.md
jxWebUI/docs/jxORM使用说明/示例.5.md
jxWebUI/docs/jxORM使用说明/继承性扩展数据.4.md
jxWebUI/docs/jxORM使用说明/编程指南.2.md
jxWebUI/docs/web组件说明/markdown.14.md
jxWebUI/docs/web组件说明/下拉选择框.11.md
jxWebUI/docs/web组件说明/代码编辑器.18.md
jxWebUI/docs/web组件说明/单选框组.12.md
jxWebUI/docs/web组件说明/图片.13.md
jxWebUI/docs/web组件说明/复选框.9.md
jxWebUI/docs/web组件说明/复选框组.13.md
jxWebUI/docs/web组件说明/多行文本框.16.md
jxWebUI/docs/web组件说明/容器表.2.md
jxWebUI/docs/web组件说明/对话框.4.md
jxWebUI/docs/web组件说明/工具条.8.md
jxWebUI/docs/web组件说明/折线图.15.md
jxWebUI/docs/web组件说明/按钮.7.md
jxWebUI/docs/web组件说明/数据表.3.md
jxWebUI/docs/web组件说明/整体说明.1.md
jxWebUI/docs/web组件说明/文本框.5.md
jxWebUI/docs/web组件说明/日期时间选择框.10.md
jxWebUI/docs/web组件说明/输入框.6.md
jxWebUI/docs/图片/ac_1.png
jxWebUI/docs/图片/bc_1.png
jxWebUI/docs/图片/bc_2.png
jxWebUI/docs/图片/bc_3.png
jxWebUI/docs/图片/bcsw_1.png
jxWebUI/docs/图片/bcsw_2.png
jxWebUI/docs/图片/bcsw_3.png
jxWebUI/docs/图片/dhk_1.png
jxWebUI/docs/图片/dt_1.png
jxWebUI/docs/图片/hello_world.png
jxWebUI/docs/图片/rqb_1.png
jxWebUI/docs/图片/sc_1.png
jxWebUI/docs/图片/sc_2.png
jxWebUI/docs/图片/sc_3.png
jxWebUI/docs/图片/sc_4.png
jxWebUI/docs/图片/test_web_1.png
jxWebUI/docs/图片/test_web_2.png
jxWebUI/docs/图片/web_1.png
jxWebUI/docs/整体说明/web界面设计说明.4.md
jxWebUI/docs/整体说明/入口.5.md
jxWebUI/docs/整体说明/前端联动计算.8.md
jxWebUI/docs/整体说明/数据表与数据库访问.6.md
jxWebUI/docs/整体说明/权限管理.9.md
jxWebUI/docs/整体说明/用户.10.md
jxWebUI/docs/整体说明/用数据表输入输出数据.7.md
jxWebUI/docs/整体说明/系统说明.1.md
jxWebUI/docs/整体说明/编程式web界面定义.3.md
jxWebUI/docs/整体说明/编程指南.2.md
jxWebUI/ui_web/__init__.py
jxWebUI/ui_web/jxUtils.py
jxWebUI/ui_web/jx_sql.py
jxWebUI/ui_web/ui_tms.py
jxWebUI/ui_web/demo/__init__.py
jxWebUI/ui_web/demo/manual.py
jxWebUI/ui_web/demo/server.py
jxWebUI/ui_web/descr/__init__.py
jxWebUI/ui_web/descr/computeSequence.py
jxWebUI/ui_web/descr/ui_python.py
jxWebUI/ui_web/descr/ui_pythonLexer.py
jxWebUI/ui_web/descr/ui_pythonListener.py
jxWebUI/ui_web/descr/ui_pythonParser.py
