Metadata-Version: 2.1
Name: jxWebUI
Version: 0.3.5
Summary: 简单易用的python Web UI库
Home-page: https://blog.csdn.net/jxandrew/article/details/148670848
Author: 徐晓轶
Author-email: andrew@pythonpi.top
Requires-Python: >=3.8
License-File: LICENSE
Requires-Dist: importlib_resources==6.4.5
Requires-Dist: pycryptodome
Requires-Dist: pytz
Requires-Dist: apscheduler
Requires-Dist: antlr4-python3-runtime==4.7.2
Requires-Dist: tornado
